polls/__init__.py
polls/admin.py
polls/apps.py
polls/models.py
polls/tests.py
polls/urls.py
polls/views.py
polls/migrations/0001_initial.py
polls/migrations/__init__.py
django_opuspolls-0.1.dist-info/METADATA
django_opuspolls-0.1.dist-info/WHEEL
django_opuspolls-0.1.dist-info/top_level.txt
django_opuspolls-0.1.dist-info/RECORD
